{
	"$schema": "http://schema.management.azure.com/schemas/2015-01-01/deploymentTemplate.json#",
	"contentVersion": "1.0.0.0",
	"parameters": {
		"factoryName": {
			"type": "string",
			"metadata": "Data Factory name",
			"defaultValue": "suryadataf"
		}
	},
	"variables": {
		"factoryId": "[concat('Microsoft.DataFactory/factories/', parameters('factoryName'))]"
	},
	"resources": [
		{
			"name": "[concat(parameters('factoryName'), '/pipeline1')]",
			"type": "Microsoft.DataFactory/factories/pipelines",
			"apiVersion": "2018-06-01",
			"properties": {
				"activities": [
					{
						"name": "Copy data1",
						"type": "Copy",
						"dependsOn": [],
						"policy": {
							"timeout": "7.00:00:00",
							"retry": 0,
							"retryIntervalInSeconds": 30,
							"secureOutput": false,
							"secureInput": false
						},
						"userProperties": [],
						"typeProperties": {
							"source": {
								"type": "AzureSqlSource",
								"queryTimeout": "02:00:00",
								"partitionOption": "None"
							},
							"sink": {
								"type": "DelimitedTextSink",
								"storeSettings": {
									"type": "AzureBlobStorageWriteSettings"
								},
								"formatSettings": {
									"type": "DelimitedTextWriteSettings",
									"quoteAllText": true,
									"fileExtension": ".txt"
								}
							},
							"enableStaging": false,
							"translator": {
								"type": "TabularTranslator",
								"typeConversion": true,
								"typeConversionSettings": {
									"allowDataTruncation": true,
									"treatBooleanAsNumber": false
								}
							}
						},
						"inputs": [
							{
								"referenceName": "SQLSourceDataset",
								"type": "DatasetReference"
							}
						],
						"outputs": [
							{
								"referenceName": "BlobDestinationDS",
								"type": "DatasetReference"
							}
						]
					}
				],
				"annotations": []
			},
			"dependsOn": [
				"[concat(variables('factoryId'), '/datasets/SQLSourceDataset')]",
				"[concat(variables('factoryId'), '/datasets/BlobDestinationDS')]"
			]
		},
		{
			"name": "[concat(parameters('factoryName'), '/BlobDestinationDS')]",
			"type": "Microsoft.DataFactory/factories/datasets",
			"apiVersion": "2018-06-01",
			"properties": {
				"linkedServiceName": {
					"referenceName": "AzureBlobStorageLS",
					"type": "LinkedServiceReference"
				},
				"annotations": [],
				"type": "DelimitedText",
				"typeProperties": {
					"location": {
						"type": "AzureBlobStorageLocation",
						"container": "outputdata"
					},
					"columnDelimiter": ",",
					"escapeChar": "\\",
					"firstRowAsHeader": true,
					"quoteChar": "\""
				},
				"schema": []
			},
			"dependsOn": []
		},
		{
			"name": "[concat(parameters('factoryName'), '/SQLSourceDataset')]",
			"type": "Microsoft.DataFactory/factories/datasets",
			"apiVersion": "2018-06-01",
			"properties": {
				"linkedServiceName": {
					"referenceName": "AzureSqlDatabase1",
					"type": "LinkedServiceReference"
				},
				"annotations": [],
				"type": "AzureSqlTable",
				"schema": [
					{
						"name": "ProductID",
						"type": "int",
						"precision": 10
					},
					{
						"name": "Name",
						"type": "nvarchar"
					},
					{
						"name": "ProductNumber",
						"type": "nvarchar"
					},
					{
						"name": "Color",
						"type": "nvarchar"
					},
					{
						"name": "StandardCost",
						"type": "money",
						"precision": 19,
						"scale": 4
					},
					{
						"name": "ListPrice",
						"type": "money",
						"precision": 19,
						"scale": 4
					},
					{
						"name": "Size",
						"type": "nvarchar"
					},
					{
						"name": "Weight",
						"type": "decimal",
						"precision": 8,
						"scale": 2
					},
					{
						"name": "ProductCategoryID",
						"type": "int",
						"precision": 10
					},
					{
						"name": "ProductModelID",
						"type": "int",
						"precision": 10
					},
					{
						"name": "SellStartDate",
						"type": "datetime",
						"precision": 23,
						"scale": 3
					},
					{
						"name": "SellEndDate",
						"type": "datetime",
						"precision": 23,
						"scale": 3
					},
					{
						"name": "DiscontinuedDate",
						"type": "datetime",
						"precision": 23,
						"scale": 3
					},
					{
						"name": "ThumbNailPhoto",
						"type": "varbinary"
					},
					{
						"name": "ThumbnailPhotoFileName",
						"type": "nvarchar"
					},
					{
						"name": "rowguid",
						"type": "uniqueidentifier"
					},
					{
						"name": "ModifiedDate",
						"type": "datetime",
						"precision": 23,
						"scale": 3
					}
				],
				"typeProperties": {
					"schema": "SalesLT",
					"table": "Product"
				}
			},
			"dependsOn": []
		}
	]
}